<PAMDataset>
  <PAMRasterBand band="1">
    <Description>Layer_1</Description>
    <Histograms>
      <HistItem>
        <HistMin>658.4039306640625</HistMin>
        <HistMax>842.6322631835938</HistMax>
        <BucketCount>256</BucketCount>
        <IncludeOutOfRange>1</IncludeOutOfRange>
        <Approximate>0</Approximate>
        <HistCounts>40|446|709|751|981|1109|1245|1165|962|709|657|547|458|394|383|358|342|389|512|403|333|286|251|207|203|189|204|195|181|169|169|185|191|213|245|279|244|245|253|241|214|240|621|1112|1359|991|1141|971|679|856|1019|801|725|687|722|833|780|858|1061|952|1021|1148|1343|1287|1182|1211|1338|1307|1392|1408|1601|1850|1862|1716|1827|1969|2141|2208|2376|2334|2314|2225|2366|2441|2652|2688|2736|2639|2767|2710|2563|2591|2570|2650|2666|2771|2827|2982|3153|3162|3391|3685|3526|3707|3909|4077|4130|4193|4335|4423|4806|4873|4766|4763|4920|5223|5311|4942|5371|5959|6081|5986|5816|6039|6278|6272|6214|6215|6194|6043|5812|5686|5580|5639|5682|5651|5761|5778|5734|5671|5847|5946|6072|5967|5792|5580|5629|5657|5647|5547|5577|5818|5756|5690|5748|5900|5791|5903|5947|6340|6108|6039|6020|6191|6204|6541|7049|6967|6806|6630|6623|6766|6759|6904|7203|7567|7577|7923|8331|8180|7470|7354|7270|8348|7271|7245|7429|7372|7456|7445|7677|7932|8119|8319|8403|8686|9028|8977|9022|9512|9719|10057|10625|11104|11578|12258|11954|11637|10799|10532|10551|10104|8222|7945|7838|7231|5959|5390|5045|4543|4239|4108|3994|4130|3737|3642|3551|3495|3678|3702|3356|3322|2837|3443|2795|1925|1699|1552|1569|1370|1301|1178|1145|1074|1083|1072|914|759|710|609|548|501|419|298|175|1</HistCounts>
      </HistItem>
    </Histograms>
    <Metadata domain="IMAGE_STRUCTURE">
      <MDI key="COMPRESSION">RLE</MDI>
    </Metadata>
    <Metadata>
      <MDI key="LAYER_TYPE">athematic</MDI>
      <MDI key="STATISTICS_MINIMUM">658.40393066406</MDI>
      <MDI key="STATISTICS_MAXIMUM">842.63226318359</MDI>
      <MDI key="STATISTICS_MEAN">774.32744853333</MDI>
      <MDI key="STATISTICS_STDDEV">35.544180220073</MDI>
      <MDI key="STATISTICS_COVARIANCES">1263.38874751704</MDI>
    </Metadata>
  </PAMRasterBand>
</PAMDataset>
